.gitignore
LICENSE
README.md
pyproject.toml
setup.py
test/test_zipfile.py
test/data/10000SalesRecords.csv
zipfile_ppmd/__init__.py
zipfile_ppmd/_patcher.py
zipfile_ppmd/_zipfile.py
zipfile_ppmd.egg-info/PKG-INFO
zipfile_ppmd.egg-info/SOURCES.txt
zipfile_ppmd.egg-info/dependency_links.txt
zipfile_ppmd.egg-info/requires.txt
zipfile_ppmd.egg-info/top_level.txt